[
  {
    "template": "clothing",
    "url": "https://www.dianxiaomi.com/web/popTemu/edit?id=128935194843933515",
    "hits": {
      "page_root": {
        "selector": "css=.product-add-layout",
        "count": 1
      },
      "shop_context": {
        "selector": "css=[routename=\"popTemuProductEdit\"]",
        "count": 1
      },
      "shop_name_control": {
        "selector": "css=.ant-form-item:has(label[title=\"店铺账号\"]) .ant-select-selector",
        "count": 1
      },
      "category_control": {
        "selector": "css=.category-item .ant-select-selector",
        "count": 1
      },
      "title_input": {
        "selector": "css=#productProductInfo .ant-form-item:has(label[title=\"产品标题\"]) input.ant-input",
        "count": 1
      },
      "english_title_input": {
        "selector": "css=#productProductInfo .ant-form-item:has(label[title=\"英文标题\"]) input.ant-input",
        "count": 1
      },
      "sku_input": {
        "selector": "placeholder=产品货号不能包含中文和中文符号",
        "count": 1
      },
      "carousel_images": {
        "selector": "css=#productProductInfo .ant-form-item.mainImage .img-list .single-image",
        "count": 5
      },
      "carousel_upload_button": {
        "selector": "css=#productProductInfo .ant-form-item.mainImage button:has-text(\"选择图片\")",
        "count": 1
      },
      "material_images": {
        "selector": "css=#productProductInfo .material-img-module .single-image",
        "count": 1
      },
      "video_uploader": {
        "selector": "css=#productProductInfo .ant-form-item:has(label[title=\"产品视频\"])",
        "count": 1
      },
      "video_upload_button": {
        "selector": "css=#productProductInfo .ant-form-item:has(label[title=\"产品视频\"]) button:has-text(\"添加视频\")",
        "count": 1
      },
      "variant_attribute_section": {
        "selector": "css=#skuAttrsInfo",
        "count": 1
      },
      "one_click_sku_button": {
        "selector": "css=#skuDataInfo th:has-text(\"SKU货号\") .link:has-text(\"一键生成\")",
        "count": 1
      },
      "sku_table": {
        "selector": "css=#skuDataInfo table.myj-table",
        "count": 2
      },
      "sku_category_batch": {
        "selector": "css=#skuDataInfo th:has-text(\"SKU分类\") .link",
        "count": 1
      },
      "packing_list_batch": {
        "selector": "css=#skuDataInfo th:has-text(\"包装清单\") .link",
        "count": 1
      },
      "description_section": {
        "selector": "css=#describeInfo",
        "count": 1
      },
      "description_images": {
        "selector": "css=#wirelessDescContentBox img",
        "count": 1
      },
      "description_editor_button": {
        "selector": "css=#describeInfo button:has-text(\"编辑描述\")",
        "count": 1
      },
      "shipping_template_dropdown": {
        "selector": "css=#shipmentInfo .ant-form-item:has(label[title=\"运费模板\"]) .ant-select-selector",
        "count": 1
      },
      "save_button": {
        "selector": "css=.footer .btn-box button:has-text(\"保存\")",
        "count": 1
      },
      "publish_button": {
        "selector": "css=.footer .btn-box button:has-text(\"发布\")",
        "count": 1
      }
    }
  },
  {
    "template": "general",
    "url": "https://www.dianxiaomi.com/web/popTemu/edit?id=128935194833519551",
    "hits": {
      "page_root": {
        "selector": "css=.product-add-layout",
        "count": 1
      },
      "shop_context": {
        "selector": "css=[routename=\"popTemuProductEdit\"]",
        "count": 1
      },
      "shop_name_control": {
        "selector": "css=.ant-form-item:has(label[title=\"店铺账号\"]) .ant-select-selector",
        "count": 1
      },
      "category_control": {
        "selector": "css=.category-item .ant-select-selector",
        "count": 1
      },
      "title_input": {
        "selector": "css=#productProductInfo .ant-form-item:has(label[title=\"产品标题\"]) input.ant-input",
        "count": 1
      },
      "english_title_input": {
        "selector": "css=#productProductInfo .ant-form-item:has(label[title=\"英文标题\"]) input.ant-input",
        "count": 1
      },
      "sku_input": {
        "selector": "placeholder=产品货号不能包含中文和中文符号",
        "count": 1
      },
      "carousel_images": {
        "selector": "css=#productProductInfo .ant-form-item.mainImage .img-list .single-image",
        "count": 5
      },
      "carousel_upload_button": {
        "selector": "css=#productProductInfo .ant-form-item.mainImage button:has-text(\"选择图片\")",
        "count": 1
      },
      "material_images": {
        "selector": "css=#productProductInfo .material-img-module .single-image",
        "count": 1
      },
      "video_uploader": {
        "selector": "css=#productProductInfo .ant-form-item:has(label[title=\"产品视频\"])",
        "count": 1
      },
      "video_upload_button": {
        "selector": "css=#productProductInfo .ant-form-item:has(label[title=\"产品视频\"]) button:has-text(\"添加视频\")",
        "count": 1
      },
      "variant_attribute_section": {
        "selector": "css=#skuAttrsInfo",
        "count": 1
      },
      "one_click_sku_button": {
        "selector": "css=#skuDataInfo th:has-text(\"SKU货号\") .link:has-text(\"一键生成\")",
        "count": 1
      },
      "sku_table": {
        "selector": "css=#skuDataInfo table.myj-table",
        "count": 2
      },
      "sku_category_batch": {
        "selector": "css=#skuDataInfo th:has-text(\"SKU分类\") .link",
        "count": 1
      },
      "packing_list_batch": {
        "selector": "css=#skuDataInfo th:has-text(\"包装清单\") .link",
        "count": 1
      },
      "description_section": {
        "selector": "css=#describeInfo",
        "count": 1
      },
      "description_images": {
        "selector": "css=#wirelessDescContentBox img",
        "count": 5
      },
      "description_editor_button": {
        "selector": "css=#describeInfo button:has-text(\"编辑描述\")",
        "count": 1
      },
      "shipping_template_dropdown": {
        "selector": "css=#shipmentInfo .ant-form-item:has(label[title=\"运费模板\"]) .ant-select-selector",
        "count": 1
      },
      "save_button": {
        "selector": "css=.footer .btn-box button:has-text(\"保存\")",
        "count": 1
      },
      "publish_button": {
        "selector": "css=.footer .btn-box button:has-text(\"发布\")",
        "count": 1
      }
    }
  }
]